Metadata-Version: 2.1
Name: ighedopassgen
Version: 1.0
License-File: LICENSE
